zerodha_data_fetcher/__init__.py
zerodha_data_fetcher/core/__init__.py
zerodha_data_fetcher/core/auth.py
zerodha_data_fetcher/core/data_fetcher.py
zerodha_data_fetcher/core/instrument_manager.py
zerodha_data_fetcher/core/rate_limiter.py
zerodha_data_fetcher/core/token_generator.py
zerodha_data_fetcher/utils/__init__.py
zerodha_data_fetcher/utils/config.py
zerodha_data_fetcher/utils/data_loader.py
zerodha_data_fetcher/utils/encryption.py
zerodha_data_fetcher/utils/exceptions.py
zerodha_data_fetcher/utils/helpers.py
zerodha_data_fetcher/utils/logging_config.py
zerodha_data_fetcher/utils/data/Kite_Instrument_ID.csv
zerodha_data_fetcher-1.0.2.dist-info/licenses/LICENSE
zerodha_data_fetcher-1.0.2.dist-info/METADATA
zerodha_data_fetcher-1.0.2.dist-info/WHEEL
zerodha_data_fetcher-1.0.2.dist-info/top_level.txt
zerodha_data_fetcher-1.0.2.dist-info/RECORD
