Metadata-Version: 2.4
Name: zerodha-data-fetcher
Version: 1.0.2
Summary: A Python package for fetching historical data from Zerodha API Using Account Credentials.
Author-email: Jayam Gupta <guptajayam47@gmail.com>
Maintainer-email: Jayam Gupta <guptajayam47@gmail.com>
License-Expression: MIT
Project-URL: Homepage, https://github.com/JayceeGupta/Zerodha-Data-Fetcher
Project-URL: Repository, https://github.com/JayceeGupta/Zerodha-Data-Fetcher
Project-URL: Documentation, https://github.com/JayceeGupta/Zerodha-Data-Fetcher#readme
Project-URL: Bug Tracker, https://github.com/JayceeGupta/Zerodha-Data-Fetcher/issues
Keywords: zerodha,trading,data,api,historical,stock-market
Classifier: Development Status :: 4 - Beta
Classifier: Intended Audience :: Developers
Classifier: Intended Audience :: Financial and Insurance Industry
Classifier: Operating System :: OS Independent
Classifier: Programming Language :: Python :: 3
Classifier: Programming Language :: Python :: 3.8
Classifier: Programming Language :: Python :: 3.9
Classifier: Programming Language :: Python :: 3.10
Classifier: Programming Language :: Python :: 3.11
Classifier: Programming Language :: Python :: 3.12
Classifier: Topic :: Office/Business :: Financial
Classifier: Topic :: Software Development :: Libraries :: Python Modules
Requires-Python: >=3.8
License-File: LICENSE
Requires-Dist: requests>=2.25.0
Requires-Dist: pandas>=1.3.0
Requires-Dist: python-dateutil>=2.8.0
Requires-Dist: pyotp>=2.6.0
Requires-Dist: keyring>=23.0.0
Requires-Dist: cryptography>=3.4.0
Requires-Dist: Brotli>=1.0.9
Requires-Dist: python-dotenv>=0.19.0
Provides-Extra: dev
Requires-Dist: pytest>=6.0; extra == "dev"
Requires-Dist: pytest-cov>=2.0; extra == "dev"
Requires-Dist: black>=21.0; extra == "dev"
Requires-Dist: flake8>=3.9; extra == "dev"
Requires-Dist: mypy>=0.910; extra == "dev"
Requires-Dist: pre-commit>=2.15; extra == "dev"
Provides-Extra: docs
Requires-Dist: sphinx>=4.0; extra == "docs"
Requires-Dist: sphinx-rtd-theme>=1.0; extra == "docs"
Requires-Dist: myst-parser>=0.15; extra == "docs"
Dynamic: license-file
